MANIFEST.in
README.rst
setup.py
virchip/__init__.py
virchip/make_expscore.py
virchip/make_input.py
virchip/predict.py
virchip/train.py
virchip/utils.py
virtualChipSeq.egg-info/PKG-INFO
virtualChipSeq.egg-info/SOURCES.txt
virtualChipSeq.egg-info/dependency_links.txt
virtualChipSeq.egg-info/not-zip-safe
virtualChipSeq.egg-info/requires.txt
virtualChipSeq.egg-info/top_level.txt