Metadata-Version: 1.1
Name: virtualChipSeq
Version: 1.2.2
Summary: Virtual ChIP-seq: predicting transcription factor binding by learning from the transcriptome
Home-page: https://bitbucket.org/hoffmanlab/proj/virtualchipseq
Author: Mehran Karimzadeh, Michael M. Hoffman
Author-email: mehran.karimzadeh@uhnresearch.ca
License: GPLv3
Platform: UNKNOWN
Classifier: Natural Language :: English
Classifier: Topic :: Scientific/Engineering :: Bio-Informatics
Classifier: Intended Audience :: Science/Research
Classifier: Operating System :: Unix
Classifier: Programming Language :: Python
Classifier: Programming Language :: Python :: 2.7
